odoo/addons/quality_control_team_oca/README.rst
odoo/addons/quality_control_team_oca/__init__.py
odoo/addons/quality_control_team_oca/__manifest__.py
odoo/addons/quality_control_team_oca/data/quality_control_team_data.xml
odoo/addons/quality_control_team_oca/i18n/de.po
odoo/addons/quality_control_team_oca/i18n/it.po
odoo/addons/quality_control_team_oca/i18n/pt.po
odoo/addons/quality_control_team_oca/i18n/pt_BR.po
odoo/addons/quality_control_team_oca/i18n/quality_control_team.pot
odoo/addons/quality_control_team_oca/i18n/quality_control_team_oca.pot
odoo/addons/quality_control_team_oca/models/__init__.py
odoo/addons/quality_control_team_oca/models/qc_team.py
odoo/addons/quality_control_team_oca/models/res_partner.py
odoo/addons/quality_control_team_oca/models/res_user.py
odoo/addons/quality_control_team_oca/readme/CONFIGURE.rst
odoo/addons/quality_control_team_oca/readme/CONTRIBUTORS.rst
odoo/addons/quality_control_team_oca/readme/DESCRIPTION.rst
odoo/addons/quality_control_team_oca/security/ir.model.access.csv
odoo/addons/quality_control_team_oca/static/description/icon.png
odoo/addons/quality_control_team_oca/static/description/icon.svg
odoo/addons/quality_control_team_oca/static/description/index.html
odoo/addons/quality_control_team_oca/tests/__init__.py
odoo/addons/quality_control_team_oca/tests/test_quality_control_team.py
odoo/addons/quality_control_team_oca/views/qc_team_dashboard.xml
odoo/addons/quality_control_team_oca/views/qc_team_view.xml
odoo13_addon_quality_control_team_oca-13.0.1.0.1.dev3.dist-info/METADATA
odoo13_addon_quality_control_team_oca-13.0.1.0.1.dev3.dist-info/WHEEL
odoo13_addon_quality_control_team_oca-13.0.1.0.1.dev3.dist-info/top_level.txt
odoo13_addon_quality_control_team_oca-13.0.1.0.1.dev3.dist-info/RECORD
